swmmio/__init__.py
swmmio/__main__.py
swmmio/core.py
swmmio/elements.py
swmmio/examples.py
swmmio/damage/__init__.py
swmmio/damage/parcels.py
swmmio/defs/__init__.py
swmmio/defs/config.py
swmmio/defs/constants.py
swmmio/defs/inp_sections.yml
swmmio/defs/section_headers.yml
swmmio/defs/sectionheaders.py
swmmio/graphics/__init__.py
swmmio/graphics/drawing.py
swmmio/graphics/profiler.py
swmmio/graphics/swmm_graphics.py
swmmio/graphics/utils.py
swmmio/graphics/fonts/Verdana.ttf
swmmio/reporting/__init__.py
swmmio/reporting/batch.py
swmmio/reporting/functions.py
swmmio/reporting/reporting.py
swmmio/reporting/serialize.py
swmmio/reporting/utils.py
swmmio/reporting/basemaps/compare.html
swmmio/reporting/basemaps/index.html
swmmio/reporting/basemaps/mapbox_base.html
swmmio/reporting/basemaps/mapbox_base_comparison.html
swmmio/run_models/__init__.py
swmmio/run_models/run.py
swmmio/run_models/start_pool.py
swmmio/tests/__init__.py
swmmio/tests/test_dataframes.py
swmmio/tests/test_functions.py
swmmio/tests/test_graphics.py
swmmio/tests/test_model_elements.py
swmmio/tests/test_run_models.py
swmmio/tests/test_spatial.py
swmmio/tests/test_version_control.py
swmmio/tests/data/Example1.inp
swmmio/tests/data/Example1.rpt
swmmio/tests/data/Example1_parallel_loop.inp
swmmio/tests/data/Example1b.inp
swmmio/tests/data/Example1b.rpt
swmmio/tests/data/Example6.inp
swmmio/tests/data/Pump_Control_Model.inp
swmmio/tests/data/SWMMExtCntrlModel.inp
swmmio/tests/data/__init__.py
swmmio/tests/data/alt_test1.inp
swmmio/tests/data/alt_test2.inp
swmmio/tests/data/alt_test3.inp
swmmio/tests/data/baseline_test.inp
swmmio/tests/data/df_test_coordinates.csv
swmmio/tests/data/groundwater_model.inp
swmmio/tests/data/invalid_model.inp
swmmio/tests/data/model-with-infiltration-parse-failure.inp
swmmio/tests/data/model_blank.inp
swmmio/tests/data/model_blank_01.inp
swmmio/tests/data/model_curve_num.inp
swmmio/tests/data/model_full_features.inp
swmmio/tests/data/model_full_features_b.inp
swmmio-0.8.2.dist-info/AUTHORS
swmmio-0.8.2.dist-info/LICENSE
swmmio-0.8.2.dist-info/METADATA
swmmio-0.8.2.dist-info/WHEEL
swmmio-0.8.2.dist-info/entry_points.txt
swmmio-0.8.2.dist-info/top_level.txt
swmmio-0.8.2.dist-info/RECORD
