Metadata-Version: 2.1
Name: swmmio
Version: 0.8.2
Summary: Tools for interacting with, editing, and visualizing EPA SWMM5 models
Home-page: https://github.com/aerispaha/swmmio
Author: Adam Erispaha
Author-email: aerispaha@gmail.com
License: MIT License
Platform: OS Independent
Classifier: Development Status :: 3 - Alpha
Classifier: License :: OSI Approved :: MIT License
Classifier: Operating System :: OS Independent
Classifier: Programming Language :: Python :: 3.7
Classifier: Programming Language :: Python :: 3.8
Classifier: Programming Language :: Python :: 3.9
Classifier: Programming Language :: Python :: 3.10
License-File: LICENSE
License-File: AUTHORS
Requires-Dist: Pillow>=6.2.0
Requires-Dist: numpy>=1.16.4
Requires-Dist: pandas>=0.24.2
Requires-Dist: pyshp>=2.1.0
Requires-Dist: geojson>=2.4.1
Requires-Dist: pyyaml>=3.12
Requires-Dist: pyproj>=3.0.0
Requires-Dist: requests>=2.32.3
Requires-Dist: typing-extensions>=4.12.2
Requires-Dist: networkx<2.8.1,>=2.3; python_version < "3.8"
Requires-Dist: networkx>=2.3; python_version >= "3.8"
